[
    1,
    0,
    0,
    [
        [
            "cc.Mesh",
            [
                "_native",
                "_hash",
                "_struct"
            ],
            1,
            11
        ]
    ],
    [
        [
            0,
            0,
            1,
            2,
            3
        ]
    ],
    [
        [
            0,
            ".bin",
            3811626380,
            [
                {
                    "primitives": [
                        {
                            "primitiveMode": 7,
                            "vertexBundelIndices": [
                                0
                            ],
                            "indexView": {
                                "offset": 4992,
                                "length": 960,
                                "count": 240,
                                "stride": 4
                            }
                        }
                    ],
                    "vertexBundles": [
                        {
                            "view": {
                                "offset": 0,
                                "length": 4992,
                                "count": 104,
                                "stride": 48
                            },
                            "attributes": [
                                {
                                    "name": "a_position",
                                    "format": 32,
                                    "isNormalized": false
                                },
                                {
                                    "name": "a_normal",
                                    "format": 32,
                                    "isNormalized": false
                                },
                                {
                                    "name": "a_texCoord",
                                    "format": 21,
                                    "isNormalized": false
                                },
                                {
                                    "name": "a_tangent",
                                    "format": 44,
                                    "isNormalized": false
                                }
                            ]
                        }
                    ]
                },
                "minPosition",
                8,
                [
                    1,
                    -0.445311576128006,
                    -0.541378915309906,
                    -4.432780542629189e-8
                ],
                "maxPosition",
                8,
                [
                    1,
                    0.44531169533729553,
                    0.00017101102275773883,
                    0.37613433599472046
                ]
            ]
        ],
        -1
    ],
    0,
    0,
    [],
    [],
    []
]
